


[{"content":" 陪你一起\n伴孩子長大 # 我是惠珊\n一名關注教育與兒童發展的 # 閱讀文章 ","date":"2026-07-01","externalUrl":null,"permalink":"/","section":"","summary":"","title":"","type":"page"},{"content":"","date":"2026-07-01","externalUrl":null,"permalink":"/posts/","section":"Posts","summary":"","title":"Posts","type":"posts"},{"content":"","date":"2026-07-01","externalUrl":null,"permalink":"/series/","section":"Series","summary":"","title":"Series","type":"series"},{"content":"","date":"2026-07-01","externalUrl":null,"permalink":"/tags/","section":"Tags","summary":"","title":"Tags","type":"tags"},{"content":"","date":"2026-07-01","externalUrl":null,"permalink":"/tags/%E5%8D%97%E5%8A%A0%E5%A4%A7/","section":"Tags","summary":"","title":"南加大","type":"tags"},{"content":"雖然還沒入學，但在準備出發的路上看著即將繳出去的學費，覺得自己一定要好好善用這一年的時間xD 因為我自己對小兒領域比較感興趣，在反覆研究課程並向學長姐老師請教的過程中，想分享一下系所提供的選課諮詢資源以及我的課程規劃。\n進入正題，南加大職能治療課程大約可以分成：\n必修課程（18 學分） 選修課程（14-18 學分） 而畢業證照 Graduate Certification ，如南加大知名的生活型態再設計 以及感覺統合課程 都是算在學分內。\n🎓 畢業規定與學分配置 # 除了必修 18 學分，還需選修 14–18 學分，且 GPA 需維持在 3.0 以上。\n【上學期】必修 10 學分 + 選修 4–8 學分 OT 500a: Clinical Problems in Occupational Therapy (2 Units) OT 512: Survey of US Health Systems (2 Units) OT 519: Foundations in Occupational Science and Occupational Therapy (3 Units) OT 526: Practice Scholar: Applying Quantitative Evidence (3 Units) 【下學期】必修 8 學分 + 選修 6–10 學分 OT 500b: Clinical Problems in Occupational Therapy (3 Units) OT 536: Practice Scholar: Applying Qualitative Evidence (3 Units) OT 540: Leadership Capstone (2 Units) 選修 (6-10 Units) Graduate Certification # 如果畢業後希望可以同時拿到 Graduate Certification，必須修滿該學程規定的課程，也就是說你的選修學分大多數會拿來上規定的課程，只剩少部分可以自由選擇運用，所以就看每個人的決定囉！\n雖然還沒有選課與上課，但基於我對小兒領域的興趣，最後選擇了 Graduate Certificate in Sensory Processing and Sensory Integration （感覺統合）的學程，原因是其中有一門課提供到診所實習的機會，不只是在一旁觀摩，而是會循序漸進地讓你練習如何進行治療，且還有一門課會在上課時針對個案進行討論，我相信會是很扎實的訓練。\n感覺統合學程 # 此學程要求的學分包含：\n【上學期】共 5 學分 + 選修剩 3 學分 OT 517: Foundations of Occupation: Sensory Processing in Daily Life (3 Units) OT 569: Sensory Integration Theory (2 Units) 3 Units remain 【上學期】共 8 學分 + 選修剩 2 學分 OT 570: Evaluation and Clinical Reasoning: Sensory Integration (2 Units) OT 610: Sensory Integrative Dysfunction (4 Units) OT 500c: Clinical Problems in Occupational Therapy (2 Units) 2 Units remain 值得注意的是，當確定完整修所有課程後，下學期的OT 500雖然只有2學分，但會安排你每週一天到一個診所進行實習，有機會實際進入美國職能治療的工作場域，從觀摩到實際帶領治療活動，只有兩學分但可以上一整天，很划算吧！如果沒有完整修所有的課程是不能獲得這個機會的喔。\n對國際學生的完整支持系統！ # 南加大職能治療學費很昂貴是不爭的事實，但同時系所也提供很多資源，讓學生在前置準備時真的時時充滿安全感。不僅包含選課，各式問題如簽證、租屋、買車等等所有問題都會迅速的找到人詢問。\n同國籍 Mentor # 系所在入學前就辦一個 Whatspp 群組，裡面有老師及學長姐可以隨時詢問問題。此外也會另外配對一位上一屆來自同國家的學長姐，可以用母語確認所有的疑問，真的是一件很有安全感的事情（保母級照顧！）。我感覺上一屆的同學之間都很熟悉，也很幸運我認識了很棒的臺灣學姊們 Jane \u0026amp; Anya，當我有疑問時總是仔細的解惑，非常可靠！\n一對一諮詢討論 # 在 2026/06/10 時，老師發送一封 email 邀請國際學生們與他約一次約30分鐘的線上會議，幫助你釐清你的興趣、目前遇到的問題並與你討論你適合選擇的課程。整個過程老師都很溫柔，能感覺得出來老師想要盡可能的支持你這一年的學習體驗。當時與他討論後發現有一堂我也想要修的課可能沒有辦法排入課表，他隨即幫我運用南加大的小友係同connect我與該領域的學姊。雖然不一定可以修完所有想要的課，但這裡的校友系統 也是一個很珍貴的資源啊！\n心得與總結 # 在排課的時候回想起大學時期最討厭的：實驗課，明明只給1學分卻要耗掉我半天的時間。 去了美國看到學費只想好好的利用所有資源，想辦法學到最多的東西，獲得更多可以寫上履歷的經驗！\n待未來實際體驗後，再來與大家分享實際修課心得！ 有任何疑問歡迎隨時與我聯繫喔\n","date":"2026-07-01","externalUrl":null,"permalink":"/posts/uscot-graduate-requirement/","section":"Posts","summary":"看著即將繳出去的昂貴學費，決定一定要好好善用學校資源！這篇將分享小兒領域、感覺統合（SI）證書課程規劃、入學前的同國籍 Mentor 制度、系所教授的線上 1 對 1 選課諮詢體驗。","title":"南加大職能治療：碩士課程與畢業規定","type":"posts"},{"content":"","date":"2026-07-01","externalUrl":null,"permalink":"/tags/%E7%95%99%E5%AD%B8%E6%BA%96%E5%82%99/","section":"Tags","summary":"","title":"留學準備","type":"tags"},{"content":"","date":"2026-07-01","externalUrl":null,"permalink":"/series/%E7%95%99%E5%AD%B8%E6%BA%96%E5%82%99%E5%8D%97%E5%8A%A0%E5%A4%A7%E8%81%B7%E8%83%BD%E6%B2%BB%E7%99%82/","section":"Series","summary":"","title":"留學準備：南加大職能治療","type":"series"},{"content":"","date":"2026-07-01","externalUrl":null,"permalink":"/tags/%E8%81%B7%E8%83%BD%E6%B2%BB%E7%99%82/","section":"Tags","summary":"","title":"職能治療","type":"tags"},{"content":"嗨大家好！我是2026 Fall 要正式就讀南加大職能治療的學生（USC OT Post-Professional MA），在出發到美國前看見系上student worker的申請機會，於是就申請並順利完成面試了！\n在準備的過程中完全沒有方向，只能依靠學長姐的記憶來準備（真的超級緊張）。所以趁著記憶猶新把經驗和時程記錄下來，希望可以幫助到未來的學弟妹們。\n今天主要會分享：\n申請的時程 準備方向與資源 面試當天的實際狀況 心得與總結 那我們就開始吧！\n申請的時程 # 整體來說準備時間還算充裕，但在等待的過程中沒有任何其他資訊所以多少會有點擔心，希望以下的分享可以幫助到學弟妹囉！\n2026/05/01 開放填寫student worker報名表單（到5/30） 2026/05/08 pre-orientation session 2026/06/11 寄信通知面試 2026/06/24 面試 準備方向與資源 # 這部分我將會分成CV（履歷）、報名表單、面試等三個階段來說明，並且提供一些當時有參考的資源，內容可能會因為目標職缺不同而略有差異，提供給大家參考。\nCV （履歷） # 這個部分相對容易，因為在申請後大部分的人應該都已經有一份現成的CV。我是使用overleaf 的模板製作，但用word完成也沒問題！如果不知道怎麼排版，可以參考哈佛大學的資源 雖然有現成版本，但我還是有重新根據這個職位的需求修改成一份應徵工作的版本，主要分成以下幾項：\nEducation （學歷） Intern Experience （實習經驗） Research Experience （研究經驗） Publication （發表） Conferences \u0026amp; Presentation （研討會與報告） Leadership （領導力） Extracurriculars （課外活動） 並不是每一個都必填！ 如果你沒有研究經歷、發表、研討會論文也沒有關係，但如果你要申請的職位和研究相關，還是盡可能地說明過去相關經驗會比較好，例如：過去製作的專題等也可以。\n另外，強烈建議可以在CV中加上「超連結」，讓教授們在面試時他們可以快速地瀏覽你的作品。舉例來說：我有放經營自媒體的Instagram帳號 @33late_ ，並說明自己過去如何透過媒體讓更多人瞭解OT，所以在面試提到時他們就可以直接點入確認，甚至當場拿官方帳號追蹤我，很酷的體驗xD\n報名表單 # 報名表單中會介紹今年開放的職位，說明這個職位的內容、以及負責管理的老師，以2026年為例，我們的職位包涵：\nAdministration（行政支援、資料追蹤） Events（協助大型活動與會議籌備） Global Initiatives（全球化計畫、支持國際學生與 SOTI 計畫） Student Ambassador（透過 Email/線上平台解答新生問題、撰寫官方部落格） Research（進入實驗室協助研究計畫、文獻回顧、數據處理） 另外需要注意的是官方有特別註明：“Students may receive only ONE student worker position in the Chan Division.”（每人只能獲得一個職位），代表不論你填幾個，最後都只會錄取其中一項，並且一週上限時數是10小時。\n在簡單的說明後，表單可以分成以下幾個部分：\nCV / Resume✅ Which Student Worker Position(s) are you applying for?✅ Personal Statement (no more than 300 words)✅ Clinical Experience (no more than 300 words) Research Experience (no more than 300 words) Clinical / Research Interests and Goals (no more than 300 words) Other Work Experience (no more than 300 words) Language Fluency Skills (no more than 300 words) Other Remarks (no more than 300 words) 基本上只有前三項必填，其餘的根據所選職位填寫即可。另外，部分項目可以直接從CV中複製貼上即可（如: 4, 5, 7, 10）。\n面試準備 # 我對自己的英文口說沒有特別有信心，但是透過網路上的資源來協助你準備面試題目是非常有幫助的，以下是我運用的資源：\nCareerVidz Dan Lok 透過這兩個頻道上建議的結構，我覺得可以有效地幫助我整理自己的經歷\n另外我也透過 Conversation exchange 與上面的英文母語人士練習英文口說，介面雖然陽春，但或許是因為使用起來很不方便所以反而覺得怪人比較少，我目前固定跟一個澳洲退休的伯伯還有一個印尼來台留學的女生保持聯繫！讓我對於口說比較不緊張！\n面試當天的實際情況 # 我大約提前3-5分鐘進入會議室等待，正式面試15-20分鐘，總共有兩位面試官輪流問你問題，但整體感覺輕鬆，不會太嚴肅或讓人覺得有壓力。後來和朋友們討論餐測面試官手上會有一個題庫，根據你選的職位挑選不同的問題，但基本上相同職位被問的是大致相同的。\n面試問題 # 以下是面試過程中的問題，沒有按照順序（我職位全選，前三志願包含Research, GI, student ambassador）：\n確認你申請的職位與排序 small talk一下（現在台灣幾點啊、目前在準備出國的感覺如何、你配對的mentor是誰） 根據你選的各個職位，你有沒有相關的經驗和優勢 會不會擔心工作和學業沒辦法兼顧 想要去的lab 做 student worker 可能遇到的挑戰 目前為止想要建議 USC OT 的東西 學期的目標和想要達到的成就 為什麼選 USC OT MA 你覺得可以怎麼樣幫助USC OT 建立更好的國際關係 你對 public speaking 多有信心？包含中文和英文 會如何和別人介紹OT 有沒有什麼問題想要問 心得與總結 # 剛面試完的時候覺得有點挫折，雖然面試官們都很友善，但我覺得沒有達到自己對於中文面試時應該有的標準，雖然現在結果尚未公布，但想要鼓勵跟我一樣對口說不太要自信的同學們：\n我們花了20多年講中文，使用英文時偶爾覺得辭不達意很正常。我們知道兩種語言，已經是一件很棒的事情了！\n過去讀書後也會越來越好的，祝福大家一切順利！\n","date":"2026-06-26","externalUrl":null,"permalink":"/posts/uscot-student-worker/","section":"Posts","summary":"剛錄取 USC OT PP-MA，出發美國前面試 student worker 職位！這篇將完整記錄從 CV 修改、報名表單填寫到面試當天被問到的 10+ 個核心問題，希望能幫助未來想申請的學弟妹們。","title":"南加大職能治療：Student Worker 申請指南與面試經驗","type":"posts"},{"content":"","date":"2026-06-26","externalUrl":null,"permalink":"/tags/%E9%9D%A2%E8%A9%A6/","section":"Tags","summary":"","title":"面試","type":"tags"},{"content":"","date":"2026-06-12","externalUrl":null,"permalink":"/policy/","section":"Policies","summary":"","title":"Policies","type":"policy"},{"content":"歡迎光臨「惠珊 職能治療師網站」（以下簡稱「本網站」）。當您瀏覽或使用本網站時，即表示您已閱讀、理解並同意接受本免責聲明之所有內容。\n一、專業醫療與衛教資訊宣告 # 本網站所刊載之所有內容（包括但不限於文字、圖片、圖表、影音及連結等），均僅供一般健康知識分享與衛教宣導參考之用，不能取代任何專業醫療人員之現場診斷、諮詢、評估或治療。 網路資訊無法完整評估個別個案之獨特身心狀況。若您或您的家人（或兒童）有任何生理、心理、發展延緩或日常生活功能上之疑慮，請務必尋求合格醫療機構、臨床醫師或職能治療師等專業醫療團隊之面對面診斷與個案評估。 讀者請勿因本網站之任何內容，而延誤就醫、忽視專業醫療建議，或自行中斷、改變正在進行中的醫療與復健計畫。因個人依據本網站資訊而自行進行之任何行為，其風險須由讀者自行承擔，本網站不負任何醫療或法律責任。 二、科學研究與資訊準確性 # 本網站之文章內容，本網站會盡力要求其正確性、即時性與客觀性。然而，醫學與科學研究日新月異，本網站無法百分之百保證所有資訊皆為最新、毫無疏漏或完全適用於所有個案。 本網站有權隨時修改、更新、刪除或暫停本網站之任何內容，而無須另行通知。 三、第三方網站連結 # 本網站之文章中，可能包含指向其他第三方網站或學術資源的連結。這些連結僅為了方便讀者學術參考或延伸閱讀而提供。該等第三方網站之內容、隱私權政策與安全性，均由各該網站擁有者自行負責，與本網站無涉。本網站亦不保證該等外部連結之準確性、即時性或完整性。\n四、智慧財產權與案例分享 # 本網站內所有原創內容之智慧財產權均屬網站創作者所有，未經書面授權，請勿擅自重製、轉載、修改或用於任何商業用途。轉載或引用部分衛教內容時，請務必註明出處與本網站連結。 本網站若有提及之臨床案例或經驗分享，均已過嚴格之**去識別化（匿名）**與情境模糊化處理，絕不涉及特定個案之隱私，亦不代表該特定干預手法對所有類似狀況之個案皆能達到完全相同之成效。 五、免責聲明之修改權利 # 本網站保留隨時修訂本免責聲明之權利。修訂後之條款將直接公佈於本網頁上，不另行個別通知。若您在修訂後繼續使用本網站，即視為您接受並同意修訂後的免責聲明。\n最近更新日期：2026 年 6 月 12 日\n","date":"2026-06-12","externalUrl":null,"permalink":"/policy/disclosure/","section":"Policies","summary":"","title":"免責聲明","type":"policy"},{"content":"歡迎光臨「惠珊 職能治療師網站」（以下簡稱本網站） ，為了維護個人隱私權與支持個人資料保護，本網站謹以下列聲明，向您說明蒐集個人資料之目的、類別、利用範圍及方式、以及您所得行使之權利等事項；如果您對於隱私權聲明、以下相關告知事項、或與個人資料保護之相關事項有任何疑問，請您和本網站聯繫，我們將儘快回覆說明。\n個人資料蒐集之目的與類別： # 本網站為了提供專業衛教資訊分享、學術交流、讀者聯絡與互動以及經營合於組織或網站定位之業務等目的，依照各服務之性質，有可能會蒐集您的姓名、連絡方式（包括但不限於電話、E-MAIL 等）、及其他得以直接或間接識別使用者身分之個人資料。\n此外，為提升服務品質，本網站會依照所提供服務之性質，記錄使用者的 IP 位址、以及在本網站相關的瀏覽活動等資料，但是這些資料僅供作流量分析和網路行為調查，以便於改善相關網站的服務品質，不會和特定個人相連繫。\n個人資料的利用： # 本網站所蒐集的足以識別使用者身分的個人資料，或日後經您同意而提供之其他個人資料，都僅供於其內部、依照蒐集之目的進行處理和利用、或為完成提供服務或履行合約義務之必要、或依照相關法令規定或有權主管機關之命令或要求，否則不會將足以識別使用者身分的個人資料提供給第三人、或移作蒐集目的以外之使用。本網站會持續保管、處理及利用相關資料。\n資料安全： # 本網站將以合於產業標準之合理技術及程序，維護個人資料之安全，防止您的個人資料遭受未經授權的存取或洩漏。\n資料當事人之權利： # 資料當事人可以請求查詢、閱覽本人的個人資料或要求給予複本。若您的個人資料有變更、或發現您的個人資料不正確，可以向本網站要求修改或更正。當蒐集個人資料之目的消失或期限屆滿時，您可要求刪除、停止處理或利用個人資料。但因執行職務或業務所必須者，不在此限。\nCookie： # 為了便利使用者，本網站可能會讀取儲存在使用者電腦中的 cookie 資料。使用者可以經由瀏覽器的設定，取消或限制此項功能，但可能因此無法使用部份網站功能。\nGoogle Analytics（分析）功能： # 本網站已安裝 Google Analytics（分析）功能。本功能僅用於分析讀者瀏覽偏好、優化網站使用流程及內容方向。如您欲停用 Google Analytics（分析）功能，建議您可參考 Google 所提供不透露資訊的方式以停用該服務。\n本隱私權政策修訂權利： # 本網站有權隨時修訂本隱私權聲明及相關告知事項，並得於修訂後公佈在網站，不另行個別通知，您可以隨時在網頁上詳閱修訂後的隱私權聲明及相關告知事項。\n最近更新日期：2026 年 6 月 12 日\n","date":"2026-06-12","externalUrl":null,"permalink":"/policy/policy/","section":"Policies","summary":"","title":"隱私權政策","type":"policy"},{"content":" 嗨！我是惠珊 # 我是一位熱愛教育的職能治療師，來自臺灣，在高雄長大，畢業於臺大職能治療系。\n我喜歡教學，不論是演講或線上線下的課程，分享自己的經驗與知識給更多有需要的人，是一件令人滿足且有成就感的事情。在幫助家長與孩子梳理方向時，每當有人告訴我：「妳分享的_____很有幫助！」，總是會讓我覺得很有意義！\n關於這個部落格 # 2022年，我開始在網路上紀錄學習方法，沒想到這些經驗意外產生共鳴，也讓我的Instagram (@33late_) 社群快速茁壯，是充滿驚喜的一件事。\n創立部落格是因為我想要記錄我的經驗，並且把專業知識簡化來支持家長與孩子。在學習的路上遇到很多人的幫助，所以現在也想要寫些文章回饋我所收到的善意。\n我的專業經歷 # 南加州大學 職能治療 碩士 （2027/5 expected） 國立台灣大學 職能治療系 學士 林口長庚醫院 實習職能治療師 台大醫院 實習職能治療師 專業證照 # 國家高等考試職能治療師證書 學術研討會 # Cheng, H.-S., Chang, T. Y., Tsao, Y., \u0026amp; Wang, H. L.* (2025, December). The application of computerized ListenTrain games for students with phonological and Chinese reading difficulties [口頭發表]. The 7th International Conference on Modern Educational Technology (ICMET-25), Fukuoka, Japan. Cheng, H.-S., Chang, Y.-C., \u0026amp; Huang, S.-L.∗ (2025, April). The efficacy of occupational therapy intervention in patients with hand osteoarthritis [海報發表]. The 25th National Taiwan University Department of Occupational Therapy Annual Conference, Taipei, Taiwan. 我的演講經歷 # 升學相關 # 2026臺大職治營：職能治療師的養成 個人申請：如何準備面試 學測倒數：如何準備學測 其他演講經歷 # 社群力變職涯力：大學生的自媒體指南 究極粉絲養成術：從平凡到不凡的自媒體修練法 青藝盟_SDGs 聯合國永續發展目標 龍安國小_SDGs 教育不平等 慢慢學習，持續成長！ # 這個部落格，不只是為了記錄我的學習與成長，也希望讓更多家庭與孩子可以獲得有價值的知識與資源。\n如果你對 數位教養、升學資源 有興趣，你可以：\n📍 追蹤我的 Facebook (更多教養相關內容)\n💌 追蹤我的Instagram (更多生活紀錄)\n✏️ 訂閱我的電子報，聽我每週碎碎念 謝謝每一個在這個社群與我相遇的你，無論你是長期關注、還是短暫停留，都是這段歷程中不可或缺的支持。未來一定還有許多挑戰，但我會持續帶著我的專業與真誠，分享更優質、實用的觀點，陪著你們一起走下去。\n","date":"2026-06-10","externalUrl":null,"permalink":"/about/","section":"","summary":"","title":"關於我：惠珊 Sabrina","type":"page"},{"content":"","date":"2022-01-25","externalUrl":null,"permalink":"/tags/about/","section":"Tags","summary":"","title":"About","type":"tags"},{"content":"","date":"2022-01-25","externalUrl":null,"permalink":"/series/documentation/","section":"Series","summary":"","title":"Documentation","type":"series"},{"content":"","date":"2022-01-25","externalUrl":null,"permalink":"/tags/first/","section":"Tags","summary":"","title":"First","type":"tags"},{"content":" Heading 1 # Heading 2 # Heading 3 # Heading 4 # Heading 3 # Heading 4 # Heading 3 # Heading 4 # Heading 5 # Heading 6 # Emphasis # Emphasis, aka italics, with asterisks or underscores.\nStrong emphasis, aka bold, with asterisks or underscores.\nCombined emphasis with asterisks and underscores.\nStrikethrough uses two tildes. Scratch this.\nLink # I\u0026rsquo;m an inline-style link I\u0026rsquo;m an inline-style link with title I\u0026rsquo;m a reference-style link I\u0026rsquo;m a relative reference to a repository file You can use numbers for reference-style link definitions Or leave it empty and use the link text itself .\nURLs and URLs in angle brackets will automatically get turned into links. http://www.example.com or http://www.example.com and sometimes example.com (but not on Github, for example).\nSome text to show that the reference links can follow later.\nParagraph # Lorem ipsum dolor sit amet consectetur adipisicing elit. Quam nihil enim maxime corporis cumque totam aliquid nam sint inventore optio modi neque laborum officiis necessitatibus, facilis placeat pariatur! Voluptatem, sed harum pariatur adipisci voluptates voluptatum cumque, porro sint minima similique magni perferendis fuga! Optio vel ipsum excepturi tempore reiciendis id quidem? Vel in, doloribus debitis nesciunt fugit sequi magnam accusantium modi neque quis, vitae velit, pariatur harum autem a! Velit impedit atque maiores animi possimus asperiores natus repellendus excepturi sint architecto eligendi non, omnis nihil. Facilis, doloremque illum. Fugit optio laborum minus debitis natus illo perspiciatis corporis voluptatum rerum laboriosam.\nList # List item List item List item List item List item Unordered List # List item List item List item List item List item Code and Syntax Highlighting # Inline code has back-ticks around it.\nvar s = \u0026#34;JavaScript syntax highlighting\u0026#34;; alert(s); s = \u0026#34;Python syntax highlighting\u0026#34; print s No language indicated, so no syntax highlighting. But let\u0026#39;s throw in a \u0026lt;b\u0026gt;tag\u0026lt;/b\u0026gt;. Blockquote # This is a blockquote example.\nInline HTML # You can also use raw HTML in your Markdown, and it\u0026rsquo;ll mostly work pretty well.\nDefinition list Is something people use sometimes. Markdown in HTML Does *not* work **very** well. Use HTML tags. Tables # Colons can be used to align columns.\nTables Are Cool col 3 is right-aligned $1600 col 2 is centered $12 zebra stripes are neat $1 There must be at least 3 dashes separating each header cell. The outer pipes (|) are optional, and you don\u0026rsquo;t need to make the raw Markdown line up prettily. You can also use inline Markdown.\nMarkdown Less Pretty Still renders nicely 1 2 3 Image # Youtube video # ","date":"2022-01-25","externalUrl":null,"permalink":"/en/posts/en-post1/","section":"Posts","summary":"了解更多关于我和我创建博客的初衷。","title":"my first posts","type":"posts"},{"content":"","date":"2022-01-25","externalUrl":null,"permalink":"/tags/new/","section":"Tags","summary":"","title":"New","type":"tags"},{"content":"","date":"2022-01-25","externalUrl":null,"permalink":"/tags/welcome/","section":"Tags","summary":"","title":"Welcome","type":"tags"},{"content":" Heading 1 # Heading 2 # Heading 3 # Heading 4 # Heading 3 # Heading 4 # Heading 3 # Heading 4 # Heading 5 # Heading 6 # Emphasis # Emphasis, aka italics, with asterisks or underscores.\nStrong emphasis, aka bold, with asterisks or underscores.\nCombined emphasis with asterisks and underscores.\nStrikethrough uses two tildes. Scratch this.\nLink # I\u0026rsquo;m an inline-style link I\u0026rsquo;m an inline-style link with title I\u0026rsquo;m a reference-style link I\u0026rsquo;m a relative reference to a repository file You can use numbers for reference-style link definitions Or leave it empty and use the link text itself .\nURLs and URLs in angle brackets will automatically get turned into links. http://www.example.com or http://www.example.com and sometimes example.com (but not on Github, for example).\nSome text to show that the reference links can follow later.\nParagraph # Lorem ipsum dolor sit amet consectetur adipisicing elit. Quam nihil enim maxime corporis cumque totam aliquid nam sint inventore optio modi neque laborum officiis necessitatibus, facilis placeat pariatur! Voluptatem, sed harum pariatur adipisci voluptates voluptatum cumque, porro sint minima similique magni perferendis fuga! Optio vel ipsum excepturi tempore reiciendis id quidem? Vel in, doloribus debitis nesciunt fugit sequi magnam accusantium modi neque quis, vitae velit, pariatur harum autem a! Velit impedit atque maiores animi possimus asperiores natus repellendus excepturi sint architecto eligendi non, omnis nihil. Facilis, doloremque illum. Fugit optio laborum minus debitis natus illo perspiciatis corporis voluptatum rerum laboriosam.\nList # List item List item List item List item List item Unordered List # List item List item List item List item List item Code and Syntax Highlighting # Inline code has back-ticks around it.\nvar s = \u0026#34;JavaScript syntax highlighting\u0026#34;; alert(s); s = \u0026#34;Python syntax highlighting\u0026#34; print s No language indicated, so no syntax highlighting. But let\u0026#39;s throw in a \u0026lt;b\u0026gt;tag\u0026lt;/b\u0026gt;. Blockquote # This is a blockquote example.\nInline HTML # You can also use raw HTML in your Markdown, and it\u0026rsquo;ll mostly work pretty well.\nDefinition list Is something people use sometimes. Markdown in HTML Does *not* work **very** well. Use HTML tags. Tables # Colons can be used to align columns.\nTables Are Cool col 3 is right-aligned $1600 col 2 is centered $12 zebra stripes are neat $1 There must be at least 3 dashes separating each header cell. The outer pipes (|) are optional, and you don\u0026rsquo;t need to make the raw Markdown line up prettily. You can also use inline Markdown.\nMarkdown Less Pretty Still renders nicely 1 2 3 Image # Youtube video # ","date":"2022-01-25","externalUrl":null,"permalink":"/posts/first-post-copy-4/","section":"Posts","summary":"了解更多关于我和我创建博客的初衷。","title":"我的第2篇posts","type":"posts"},{"content":" Heading 1 # Heading 2 # Heading 3 # Heading 4 # Heading 3 # Heading 4 # Heading 3 # Heading 4 # Heading 5 # Heading 6 # Emphasis # Emphasis, aka italics, with asterisks or underscores.\nStrong emphasis, aka bold, with asterisks or underscores.\nCombined emphasis with asterisks and underscores.\nStrikethrough uses two tildes. Scratch this.\nLink # I\u0026rsquo;m an inline-style link I\u0026rsquo;m an inline-style link with title I\u0026rsquo;m a reference-style link I\u0026rsquo;m a relative reference to a repository file You can use numbers for reference-style link definitions Or leave it empty and use the link text itself .\nURLs and URLs in angle brackets will automatically get turned into links. http://www.example.com or http://www.example.com and sometimes example.com (but not on Github, for example).\nSome text to show that the reference links can follow later.\nParagraph # Lorem ipsum dolor sit amet consectetur adipisicing elit. Quam nihil enim maxime corporis cumque totam aliquid nam sint inventore optio modi neque laborum officiis necessitatibus, facilis placeat pariatur! Voluptatem, sed harum pariatur adipisci voluptates voluptatum cumque, porro sint minima similique magni perferendis fuga! Optio vel ipsum excepturi tempore reiciendis id quidem? Vel in, doloribus debitis nesciunt fugit sequi magnam accusantium modi neque quis, vitae velit, pariatur harum autem a! Velit impedit atque maiores animi possimus asperiores natus repellendus excepturi sint architecto eligendi non, omnis nihil. Facilis, doloremque illum. Fugit optio laborum minus debitis natus illo perspiciatis corporis voluptatum rerum laboriosam.\nList # List item List item List item List item List item Unordered List # List item List item List item List item List item Code and Syntax Highlighting # Inline code has back-ticks around it.\nvar s = \u0026#34;JavaScript syntax highlighting\u0026#34;; alert(s); s = \u0026#34;Python syntax highlighting\u0026#34; print s No language indicated, so no syntax highlighting. But let\u0026#39;s throw in a \u0026lt;b\u0026gt;tag\u0026lt;/b\u0026gt;. Blockquote # This is a blockquote example.\nInline HTML # You can also use raw HTML in your Markdown, and it\u0026rsquo;ll mostly work pretty well.\nDefinition list Is something people use sometimes. Markdown in HTML Does *not* work **very** well. Use HTML tags. Tables # Colons can be used to align columns.\nTables Are Cool col 3 is right-aligned $1600 col 2 is centered $12 zebra stripes are neat $1 There must be at least 3 dashes separating each header cell. The outer pipes (|) are optional, and you don\u0026rsquo;t need to make the raw Markdown line up prettily. You can also use inline Markdown.\nMarkdown Less Pretty Still renders nicely 1 2 3 Image # Youtube video # ","date":"2022-01-25","externalUrl":null,"permalink":"/posts/first-post-copy-5/","section":"Posts","summary":"了解更多关于我和我创建博客的初衷。","title":"我的第3篇posts","type":"posts"},{"content":"","externalUrl":null,"permalink":"/authors/","section":"Authors","summary":"","title":"Authors","type":"authors"},{"content":"","externalUrl":null,"permalink":"/categories/","section":"Categories","summary":"","title":"Categories","type":"categories"}]